main.py
songzhihao-0.1.dist-info/METADATA
songzhihao-0.1.dist-info/WHEEL
songzhihao-0.1.dist-info/entry_points.txt
songzhihao-0.1.dist-info/top_level.txt
songzhihao-0.1.dist-info/RECORD
