Metadata-Version: 2.1
Name: songzhihao
Version: 0.1
Requires-Dist: Click
